decor/__init__.py
decor/_decor.cp36-win_amd64.pyd
decor/background.py
decor/beamline.py
decor/darkcurrent.py
decor/distortion.py
decor/floodfield.py
decor/incidence.py
decor/mask.py
decor/normalization.py
decor/spline.py
decor-2018.7.9.dist-info/METADATA
decor-2018.7.9.dist-info/RECORD
decor-2018.7.9.dist-info/WHEEL
decor-2018.7.9.dist-info/top_level.txt
