Metadata-Version: 2.1
Name: decor
Version: 2018.7.9
Summary: Detector corrections for azimuthal integration
Home-page: https://hg.3lp.cx/decor
Author: Vadim Dyadkin
Author-email: dyadkin@gmail.com
License: GPLv3
Platform: UNKNOWN
Classifier: License :: OSI Approved :: GNU General Public License v3 (GPLv3)
Classifier: Programming Language :: Python
Classifier: Programming Language :: Python :: 3.6
Classifier: Programming Language :: Python :: Implementation :: CPython
Requires-Dist: numpy
Requires-Dist: cryio
